asf_common_services/__init__.py
asf_common_services/service_config.py
asf_common_services/service_layer.py
asf_common_services/cache/__init__.py
asf_common_services/cache/redis_cache.py
asf_common_services/database/__init__.py
asf_common_services/database/mongodb.py
asf_common_services/messaging/__init__.py
asf_common_services/messaging/kafka_messaging.py
asf_common_services/models/__init__.py
asf_common_services/models/chain_pb2.py
asf_common_services/models/chain_pb2.pyi
asf_common_services/models/chains_pb2.py
asf_common_services/models/chains_pb2.pyi
asf_common_services/models/request_pb2.py
asf_common_services/models/request_pb2.pyi
asf_common_services/models/schedule_config_pb2.py
asf_common_services/models/schedule_config_pb2.pyi
asf_common_services-0.0.2.dist-info/METADATA
asf_common_services-0.0.2.dist-info/WHEEL
asf_common_services-0.0.2.dist-info/top_level.txt
asf_common_services-0.0.2.dist-info/RECORD
