Metadata-Version: 2.1
Name: asf-common-services
Version: 0.0.2
Requires-Dist: protobuf
